README.md
scarfing/__init__.py
scarfing/py.typed
scarfing-0.1.0.dist-info/METADATA
scarfing-0.1.0.dist-info/WHEEL
scarfing-0.1.0.dist-info/RECORD
